{"Yorafa":{"user":"Yorafa","total":5,"easy_cnt":2,"medium_cnt":3,"hard_cnt":0,"easy":["delete-columns-to-make-sorted","two-sum"],"medium":["minimum-rounds-to-complete-all-tasks","minimum-number-of-arrows-to-burst-balloons","maximum-ice-cream-bars"],"hard":[]},"zhuyuezx":{"user":"zhuyuezx","total":11,"easy_cnt":1,"medium_cnt":4,"hard_cnt":6,"easy":["delete-columns-to-make-sorted"],"medium":["best-team-with-no-conflicts","minimum-rounds-to-complete-all-tasks","minimum-number-of-arrows-to-burst-balloons","maximum-ice-cream-bars"],"hard":["divide-chocolate","maximum-frequency-stack","minimum-distance-to-type-a-word-using-two-fingers","sudoku-solver","count-of-smaller-numbers-after-self","constrained-subsequence-sum"]},"Ethan-ZYF":{"user":"Ethan-ZYF","total":13,"easy_cnt":3,"medium_cnt":9,"hard_cnt":1,"easy":["delete-columns-to-make-sorted","root-equals-sum-of-children","remove-outermost-parentheses"],"medium":["search-a-2d-matrix","k-highest-ranked-items-within-a-price-range","minimum-cost-to-set-cooking-time","count-the-hidden-sequences","rearrange-array-elements-by-sign","minimum-rounds-to-complete-all-tasks","minimum-number-of-arrows-to-burst-balloons","maximum-ice-cream-bars","count-primes"],"hard":["number-of-ways-to-reconstruct-a-tree"]},"jmyanxiang":{"user":"jmyanxiang","total":8,"easy_cnt":3,"medium_cnt":5,"hard_cnt":0,"easy":["confusing-number","detect-capital","delete-columns-to-make-sorted"],"medium":["domino-and-tromino-tiling","evaluate-reverse-polish-notation","longest-nice-subarray","smallest-subarrays-with-maximum-bitwise-or","merge-operations-to-turn-array-into-a-palindrome"],"hard":[]},"nopespace":{"user":"nopespace","total":0,"easy_cnt":0,"medium_cnt":0,"hard_cnt":0,"easy":[],"medium":[],"hard":[]},"huiyu2802":{"user":"huiyu2802","total":0,"easy_cnt":0,"medium_cnt":0,"hard_cnt":0,"easy":[],"medium":[],"hard":[]},"Roccay":{"user":"Roccay","total":0,"easy_cnt":0,"medium_cnt":0,"hard_cnt":0,"easy":[],"medium":[],"hard":[]},"jasongangquanzhang":{"user":"jasongangquanzhang","total":0,"easy_cnt":0,"medium_cnt":0,"hard_cnt":0,"easy":[],"medium":[],"hard":[]},"roxanehe":{"user":"roxanehe","total":0,"easy_cnt":0,"medium_cnt":0,"hard_cnt":0,"easy":[],"medium":[],"hard":[]}}