{"2023-01-24":{"user":"Deuterium_w","total":7,"easy_cnt":7,"medium_cnt":0,"hard_cnt":0,"easy":["richest-customer-wealth","running-sum-of-1d-array","add-two-integers","number-of-steps-to-reduce-a-number-to-zero","fizz-buzz","middle-of-the-linked-list","ransom-note"],"medium":[],"hard":[]},"2023-01-25":{"user":"Deuterium_w","total":6,"easy_cnt":0,"medium_cnt":0,"hard_cnt":6,"easy":[],"medium":[],"hard":["two-sum","add-two-numbers","longest-substring-without-repeating-characters","median-of-two-sorted-arrays","zigzag-conversion","reverse-integer"]},"2023-01-26":{"user":"Deuterium_w","total":1,"easy_cnt":0,"medium_cnt":0,"hard_cnt":1,"easy":[],"medium":[],"hard":["palindrome-number"]},"2023-01-27":{"user":"Deuterium_w","total":1,"easy_cnt":0,"medium_cnt":0,"hard_cnt":1,"easy":[],"medium":[],"hard":["string-to-integer-atoi"]},"2023-02-02":{"user":"Deuterium_w","total":1,"easy_cnt":0,"medium_cnt":0,"hard_cnt":1,"easy":[],"medium":[],"hard":["integer-to-roman"]},"2023-02-19":{"user":"Deuterium_w","total":2,"easy_cnt":1,"medium_cnt":0,"hard_cnt":1,"easy":["invert-binary-tree"],"medium":[],"hard":["search-insert-position"]}}