{"2023-01-17":{"user":"enmeng_l","total":1,"easy_cnt":0,"medium_cnt":1,"hard_cnt":0,"easy":[],"medium":["palindrome-partitioning"],"hard":[]},"2023-01-16":{"user":"enmeng_l","total":1,"easy_cnt":0,"medium_cnt":1,"hard_cnt":0,"easy":[],"medium":["surrounded-regions"],"hard":[]},"2023-01-15":{"user":"enmeng_l","total":1,"easy_cnt":0,"medium_cnt":1,"hard_cnt":0,"easy":[],"medium":["longest-consecutive-sequence"],"hard":[]},"2023-01-14":{"user":"enmeng_l","total":2,"easy_cnt":0,"medium_cnt":2,"hard_cnt":0,"easy":[],"medium":["best-time-to-buy-and-sell-stock-ii","populating-next-right-pointers-in-each-node"],"hard":[]},"2023-01-13":{"user":"enmeng_l","total":2,"easy_cnt":0,"medium_cnt":2,"hard_cnt":0,"easy":[],"medium":["construct-binary-tree-from-preorder-and-inorder-traversal","binary-tree-zigzag-level-order-traversal"],"hard":[]},"2023-01-12":{"user":"enmeng_l","total":1,"easy_cnt":0,"medium_cnt":1,"hard_cnt":0,"easy":[],"medium":["binary-tree-level-order-traversal"],"hard":[]},"2023-01-11":{"user":"enmeng_l","total":1,"easy_cnt":0,"medium_cnt":0,"hard_cnt":1,"easy":[],"medium":[],"hard":["validate-binary-search-tree"]},"2023-01-10":{"user":"enmeng_l","total":1,"easy_cnt":0,"medium_cnt":0,"hard_cnt":1,"easy":[],"medium":[],"hard":["decode-ways"]},"2023-01-09":{"user":"enmeng_l","total":1,"easy_cnt":0,"medium_cnt":0,"hard_cnt":1,"easy":[],"medium":[],"hard":["word-search"]},"2023-01-08":{"user":"enmeng_l","total":1,"easy_cnt":0,"medium_cnt":0,"hard_cnt":1,"easy":[],"medium":[],"hard":["subsets"]},"2023-01-07":{"user":"enmeng_l","total":1,"easy_cnt":0,"medium_cnt":0,"hard_cnt":1,"easy":[],"medium":[],"hard":["sort-colors"]},"2023-01-04":{"user":"enmeng_l","total":1,"easy_cnt":0,"medium_cnt":0,"hard_cnt":1,"easy":[],"medium":[],"hard":["set-matrix-zeroes"]},"2023-01-03":{"user":"enmeng_l","total":1,"easy_cnt":0,"medium_cnt":0,"hard_cnt":1,"easy":[],"medium":[],"hard":["unique-paths"]},"2022-12-31":{"user":"enmeng_l","total":3,"easy_cnt":0,"medium_cnt":0,"hard_cnt":3,"easy":[],"medium":[],"hard":["merge-intervals","jump-game","spiral-matrix"]},"2022-12-30":{"user":"enmeng_l","total":2,"easy_cnt":0,"medium_cnt":1,"hard_cnt":1,"easy":[],"medium":["powx-n"],"hard":["maximum-subarray"]},"2023-01-18":{"user":"enmeng_l","total":1,"easy_cnt":0,"medium_cnt":1,"hard_cnt":0,"easy":[],"medium":["gas-station"],"hard":[]},"2023-01-19":{"user":"enmeng_l","total":1,"easy_cnt":0,"medium_cnt":1,"hard_cnt":0,"easy":[],"medium":["copy-list-with-random-pointer"],"hard":[]},"2023-01-21":{"user":"enmeng_l","total":2,"easy_cnt":0,"medium_cnt":2,"hard_cnt":0,"easy":[],"medium":["word-break","lru-cache"],"hard":[]},"2023-01-22":{"user":"enmeng_l","total":1,"easy_cnt":0,"medium_cnt":1,"hard_cnt":0,"easy":[],"medium":["sort-list"],"hard":[]},"2023-01-23":{"user":"enmeng_l","total":1,"easy_cnt":0,"medium_cnt":1,"hard_cnt":0,"easy":[],"medium":["evaluate-reverse-polish-notation"],"hard":[]},"2023-01-24":{"user":"enmeng_l","total":1,"easy_cnt":0,"medium_cnt":1,"hard_cnt":0,"easy":[],"medium":["maximum-product-subarray"],"hard":[]},"2023-01-25":{"user":"enmeng_l","total":1,"easy_cnt":0,"medium_cnt":1,"hard_cnt":0,"easy":[],"medium":["min-stack"],"hard":[]},"2023-01-26":{"user":"enmeng_l","total":1,"easy_cnt":0,"medium_cnt":1,"hard_cnt":0,"easy":[],"medium":["find-peak-element"],"hard":[]}}