{"Ethan-ZYF":{"user":"Ethan-ZYF","total":5,"easy_cnt":4,"medium_cnt":1,"hard_cnt":0,"easy":["power-of-three","largest-3-same-digit-number-in-string","power-of-four","maximum-69-number"],"medium":["range-product-queries-of-powers"],"hard":[]},"jmyanxiang":{"user":"jmyanxiang","total":5,"easy_cnt":1,"medium_cnt":3,"hard_cnt":1,"easy":["power-of-three"],"medium":["xor-after-range-multiplication-queries-i","minimum-sum-after-divisible-sum-deletions","best-time-to-buy-and-sell-stock-using-strategy"],"hard":["xor-after-range-multiplication-queries-ii"]},"huiyu2802":{"user":"huiyu2802","total":6,"easy_cnt":0,"medium_cnt":2,"hard_cnt":4,"easy":[],"medium":["xor-after-range-multiplication-queries-i","best-time-to-buy-and-sell-stock-using-strategy"],"hard":["word-ladder","n-queens-ii","ipo","word-search-ii"]},"HLeiTR":{"user":"HLeiTR","total":21,"easy_cnt":6,"medium_cnt":14,"hard_cnt":1,"easy":["power-of-three","largest-3-same-digit-number-in-string","maximum-69-number","keep-multiplying-found-values-by-two","number-of-even-and-odd-bits","decode-xored-array"],"medium":["range-product-queries-of-powers","count-number-of-texts","find-the-substring-with-maximum-cost","maximum-sum-circular-subarray","k-concatenation-maximum-sum","letter-tile-possibilities","longest-consecutive-sequence","count-paths-with-the-given-xor-value","generate-binary-strings-without-adjacent-zeros","maximum-xor-after-operations","find-xor-beauty-of-array","substring-xor-queries","xor-after-range-multiplication-queries-i","best-time-to-buy-and-sell-stock-using-strategy"],"hard":["ways-to-express-an-integer-as-sum-of-powers"]},"joseTheJalapeno":{"user":"joseTheJalapeno","total":2,"easy_cnt":1,"medium_cnt":0,"hard_cnt":1,"easy":["power-of-three"],"medium":[],"hard":["ways-to-express-an-integer-as-sum-of-powers"]},"Yorafa":{"user":"Yorafa","total":0,"easy_cnt":0,"medium_cnt":0,"hard_cnt":0,"easy":[],"medium":[],"hard":[]},"zhuyuezx":{"user":"zhuyuezx","total":0,"easy_cnt":0,"medium_cnt":0,"hard_cnt":0,"easy":[],"medium":[],"hard":[]},"nopespace":{"user":"nopespace","total":0,"easy_cnt":0,"medium_cnt":0,"hard_cnt":0,"easy":[],"medium":[],"hard":[]},"Roccay":{"user":"Roccay","total":0,"easy_cnt":0,"medium_cnt":0,"hard_cnt":0,"easy":[],"medium":[],"hard":[]},"jasongangquanzhang":{"user":"jasongangquanzhang","total":0,"easy_cnt":0,"medium_cnt":0,"hard_cnt":0,"easy":[],"medium":[],"hard":[]},"roxanehe":{"user":"roxanehe","total":0,"easy_cnt":0,"medium_cnt":0,"hard_cnt":0,"easy":[],"medium":[],"hard":[]},"LittleAnt2023":{"user":"LittleAnt2023","total":0,"easy_cnt":0,"medium_cnt":0,"hard_cnt":0,"easy":[],"medium":[],"hard":[]},"GoneZzoe":{"user":"GoneZzoe","total":0,"easy_cnt":0,"medium_cnt":0,"hard_cnt":0,"easy":[],"medium":[],"hard":[]},"zhumengzhiren":{"user":"zhumengzhiren","total":0,"easy_cnt":0,"medium_cnt":0,"hard_cnt":0,"easy":[],"medium":[],"hard":[]},"ElizaZoldyck":{"user":"ElizaZoldyck","total":0,"easy_cnt":0,"medium_cnt":0,"hard_cnt":0,"easy":[],"medium":[],"hard":[]},"jadenzhang12345":{"user":"jadenzhang12345","total":0,"easy_cnt":0,"medium_cnt":0,"hard_cnt":0,"easy":[],"medium":[],"hard":[]},"Y11111111":{"user":"Y11111111","total":0,"easy_cnt":0,"medium_cnt":0,"hard_cnt":0,"easy":[],"medium":[],"hard":[]},"frankqiaowxl2":{"user":"frankqiaowxl2","total":0,"easy_cnt":0,"medium_cnt":0,"hard_cnt":0,"easy":[],"medium":[],"hard":[]},"enmeng_l":{"user":"enmeng_l","total":0,"easy_cnt":0,"medium_cnt":0,"hard_cnt":0,"easy":[],"medium":[],"hard":[]},"YukiJudaiii":{"user":"YukiJudaiii","total":0,"easy_cnt":0,"medium_cnt":0,"hard_cnt":0,"easy":[],"medium":[],"hard":[]},"ScottCTD":{"user":"ScottCTD","total":0,"easy_cnt":0,"medium_cnt":0,"hard_cnt":0,"easy":[],"medium":[],"hard":[]},"torpedooes":{"user":"torpedooes","total":0,"easy_cnt":0,"medium_cnt":0,"hard_cnt":0,"easy":[],"medium":[],"hard":[]},"xiuyuyuan712":{"user":"xiuyuyuan712","total":0,"easy_cnt":0,"medium_cnt":0,"hard_cnt":0,"easy":[],"medium":[],"hard":[]},"Deuterium_w":{"user":"Deuterium_w","total":0,"easy_cnt":0,"medium_cnt":0,"hard_cnt":0,"easy":[],"medium":[],"hard":[]},"fengzhe2002":{"user":"fengzhe2002","total":0,"easy_cnt":0,"medium_cnt":0,"hard_cnt":0,"easy":[],"medium":[],"hard":[]},"ZuiYue1":{"user":"ZuiYue1","total":0,"easy_cnt":0,"medium_cnt":0,"hard_cnt":0,"easy":[],"medium":[],"hard":[]},"Steph_Zha":{"user":"Steph_Zha","total":0,"easy_cnt":0,"medium_cnt":0,"hard_cnt":0,"easy":[],"medium":[],"hard":[]}}